tracer/__init__.py
tracer/interaction_tracer.py
tracer/io_blocking_tracer.py
tracer/tracer.py
tracer/qemu/__init__.py
tracer/qemu/build.py
tracer/qemu/bin/qemu-x86_64
cartprograph-0.2.3.dist-info/METADATA
cartprograph-0.2.3.dist-info/WHEEL
cartprograph-0.2.3.dist-info/top_level.txt
cartprograph-0.2.3.dist-info/RECORD
