Metadata-Version: 2.1
Name: cartprograph
Version: 0.2.3
Summary: UNKNOWN
Home-page: UNKNOWN
License: UNKNOWN
Platform: UNKNOWN
Requires-Python: >=3.8
Requires-Dist: setuptools
Requires-Dist: networkx
Requires-Dist: flask
Requires-Dist: flask-socketio
Requires-Dist: eventlet
Requires-Dist: redis
Requires-Dist: archr
